{
    "uuid": [
        {
            "value": "d50db080-1ac6-4c1d-b1c3-ca2e8be0038e"
        }
    ],
    "langcode": [
        {
            "value": "es"
        }
    ],
    "type": [
        {
            "target_id": "coleccion",
            "target_type": "node_type",
            "target_uuid": "ce153234-b925-4819-98de-11e2767af89e"
        }
    ],
    "revision_timestamp": [
        {
            "value": "2020-10-31T20:23:33+00:00",
            "format": "Y-m-d\\TH:i:sP"
        }
    ],
    "revision_uid": [
        {
            "target_type": "user",
            "target_uuid": "5abe7d29-b959-4c2f-bdcc-073fa45a4be7"
        }
    ],
    "revision_log": [],
    "status": [
        {
            "value": true
        }
    ],
    "uid": [
        {
            "target_type": "user",
            "target_uuid": "5abe7d29-b959-4c2f-bdcc-073fa45a4be7"
        }
    ],
    "title": [
        {
            "value": "Sunday, November 1 del 2020"
        }
    ],
    "created": [
        {
            "value": "2020-10-31T20:16:01+00:00",
            "format": "Y-m-d\\TH:i:sP"
        }
    ],
    "changed": [
        {
            "value": "2020-10-31T20:23:33+00:00",
            "format": "Y-m-d\\TH:i:sP"
        }
    ],
    "promote": [
        {
            "value": true
        }
    ],
    "sticky": [
        {
            "value": false
        }
    ],
    "default_langcode": [
        {
            "value": true
        }
    ],
    "revision_translation_affected": [
        {
            "value": true
        }
    ],
    "path": [
        {
            "alias": "\/colecciones\/domingo-noviembre-1-del-2020",
            "langcode": "es",
            "pathauto": 1
        }
    ],
    "field_canciones": [
        {
            "target_type": "node",
            "target_uuid": "718569a0-8b39-45e4-ba02-8191d53a9a4d"
        },
        {
            "target_type": "node",
            "target_uuid": "b856bbdc-a92e-43b2-a462-cf7a66a3cb5a"
        },
        {
            "target_type": "node",
            "target_uuid": "f6106733-aa99-46d1-8c47-0623b3703e06"
        },
        {
            "target_type": "node",
            "target_uuid": "3455f529-719f-4d55-91e8-5834a4d03cab"
        },
        {
            "target_type": "node",
            "target_uuid": "d397cc39-615e-4eb1-9e62-fec1e4143a5e"
        },
        {
            "target_type": "node",
            "target_uuid": "0a93bbd9-6348-482f-a26e-42415f2863ed"
        }
    ],
    "field_descripcion": [],
    "field_fecha_y_hora": [
        {
            "value": "2020-11-01T09:00:00-06:00"
        }
    ]
}