{
    "uuid": [
        {
            "value": "be58afd3-cfd9-4a62-86d2-22a2e91bd422"
        }
    ],
    "langcode": [
        {
            "value": "es"
        }
    ],
    "type": [
        {
            "target_id": "cancion",
            "target_type": "node_type",
            "target_uuid": "28b6703e-a729-4c5a-afca-0fe5c2df3b65"
        }
    ],
    "revision_timestamp": [
        {
            "value": "2021-06-24T19:29:22+00:00",
            "format": "Y-m-d\\TH:i:sP"
        }
    ],
    "revision_uid": [
        {
            "target_type": "user",
            "target_uuid": "c77c2a62-9f5e-4f4e-997b-26378e657673"
        }
    ],
    "revision_log": [],
    "status": [
        {
            "value": true
        }
    ],
    "uid": [
        {
            "target_type": "user",
            "target_uuid": "c77c2a62-9f5e-4f4e-997b-26378e657673"
        }
    ],
    "title": [
        {
            "value": "Dios de esta ciudad"
        }
    ],
    "created": [
        {
            "value": "2019-12-30T04:47:37+00:00",
            "format": "Y-m-d\\TH:i:sP"
        }
    ],
    "changed": [
        {
            "value": "2021-06-24T19:29:22+00:00",
            "format": "Y-m-d\\TH:i:sP"
        }
    ],
    "promote": [
        {
            "value": true
        }
    ],
    "sticky": [
        {
            "value": false
        }
    ],
    "default_langcode": [
        {
            "value": true
        }
    ],
    "revision_translation_affected": [
        {
            "value": true
        }
    ],
    "path": [
        {
            "alias": "\/canciones\/blest\/dios-de-esta-ciudad",
            "langcode": "es",
            "pathauto": 1
        }
    ],
    "field_artista": [
        {
            "target_type": "taxonomy_term",
            "target_uuid": "a37a1362-9916-4e19-89b6-70b64a0a0348"
        }
    ],
    "field_bpm": [],
    "field_descripcion": [],
    "field_letra": [
        {
            "value": "<p>&nbsp;&lt;lyrics&gt;[V]&nbsp;<br \/>\r\n&nbsp;T\u00fa eres rey de este pueblo<br \/>\r\n&nbsp;Eres Dios en esta ciudad<br \/>\r\n&nbsp;El Se\u00f1or de esta naci\u00f3n,<br \/>\r\n&nbsp;Eres Dios||<\/p>\r\n\r\n<p>&nbsp;Eres nuestra esperanza<br \/>\r\n&nbsp;Eres luz en la oscuridad<br \/>\r\n&nbsp;Eres paz al cansado,<br \/>\r\n&nbsp;Eres Dios<\/p>\r\n\r\n<p>[P]<br \/>\r\n&nbsp;No hay otro como Tu<br \/>\r\n&nbsp;No hay otro como Tu<\/p>\r\n\r\n<p>[C]<br \/>\r\n&nbsp;--<br \/>\r\n&nbsp;Grandes cosas vienen ya<br \/>\r\n&nbsp;Grandes cosas Dios har\u00e1<br \/>\r\n&nbsp;en este pueblo||<br \/>\r\n&nbsp;-<br \/>\r\n&nbsp;Grandes cosas vienen ya<br \/>\r\n&nbsp;Grandes cosas Dios har\u00e1<br \/>\r\n&nbsp;en este pueblo<\/p>\r\n\r\n<p>[C2]<br \/>\r\n&nbsp;----<br \/>\r\n&nbsp;Grandes cosas vienen ya<br \/>\r\n&nbsp;Grandes cosas Dios har\u00e1<br \/>\r\n&nbsp;en este pueblo||<br \/>\r\n&nbsp;---<br \/>\r\n&nbsp;Grandes cosas vienen ya<br \/>\r\n&nbsp;Grandes cosas Dios har\u00e1<br \/>\r\n&nbsp;en este pueblo||<br \/>\r\n&nbsp;--<br \/>\r\n&nbsp;Grandes cosas vienen ya<br \/>\r\n&nbsp;Grandes cosas Dios har\u00e1<br \/>\r\n&nbsp;en este pueblo||<br \/>\r\n&nbsp;-<br \/>\r\n&nbsp;Grandes cosas vienen ya<br \/>\r\n&nbsp;Grandes cosas Dios har\u00e1<br \/>\r\n&nbsp;en este pueblo<\/p>\r\n\r\n<p>[T]<br \/>\r\n&nbsp;Grandes cosas vienen ya<br \/>\r\n&nbsp;Grandes cosas Dios har\u00e1<\/p>\r\n\r\n<p>[I]<br \/>\r\n&nbsp;\u266b<\/p>\r\n\r\n<p>&lt;\/lyrics&gt;<br \/>\r\n&nbsp; &lt;presentation&gt;V P C V P C T I P C2 T&lt;\/presentation&gt;<\/p>\r\n\r\n<div id=\"gtx-trans\" style=\"position: absolute; left: 298px; top: 1832px;\">\r\n<div class=\"gtx-trans-icon\">&nbsp;<\/div>\r\n<\/div>\r\n",
            "format": "basic_html"
        }
    ],
    "field_multitrack": [],
    "field_recursos": [],
    "field_secuencia": [
        {
            "uri": "https:\/\/drive.google.com\/file\/d\/1gQjh1cdQ-Yekj0oy-DdNA9s3zHEI1f0L\/view?usp=sharing",
            "title": "",
            "options": []
        }
    ],
    "field_tags": [],
    "field_tipo": [
        {
            "value": "Lenta"
        }
    ],
    "field_tipo_de_voz": [
        {
            "value": "Masculina"
        }
    ],
    "field_tono": [
        {
            "target_type": "taxonomy_term",
            "target_uuid": "77081126-b90f-456f-b893-1fa4982791ca"
        }
    ],
    "field_video": [
        {
            "value": "https:\/\/www.youtube.com\/watch?v=l0ByAD5ttaE"
        }
    ]
}