{
    "uuid": [
        {
            "value": "bebeea6a-8052-4480-bcb6-8701cf37c0a5"
        }
    ],
    "langcode": [
        {
            "value": "es"
        }
    ],
    "type": [
        {
            "target_id": "cancion",
            "target_type": "node_type",
            "target_uuid": "28b6703e-a729-4c5a-afca-0fe5c2df3b65"
        }
    ],
    "revision_timestamp": [
        {
            "value": "2021-12-16T02:07:18+00:00",
            "format": "Y-m-d\\TH:i:sP"
        }
    ],
    "revision_uid": [
        {
            "target_type": "user",
            "target_uuid": "45377d3b-f5ac-4d61-9bca-94accc26d36a"
        }
    ],
    "revision_log": [],
    "status": [
        {
            "value": true
        }
    ],
    "uid": [
        {
            "target_type": "user",
            "target_uuid": "45377d3b-f5ac-4d61-9bca-94accc26d36a"
        }
    ],
    "title": [
        {
            "value": "Amarte es un deleite"
        }
    ],
    "created": [
        {
            "value": "2021-12-16T02:05:52+00:00",
            "format": "Y-m-d\\TH:i:sP"
        }
    ],
    "changed": [
        {
            "value": "2022-02-01T00:52:47+00:00",
            "format": "Y-m-d\\TH:i:sP"
        }
    ],
    "promote": [
        {
            "value": true
        }
    ],
    "sticky": [
        {
            "value": false
        }
    ],
    "default_langcode": [
        {
            "value": true
        }
    ],
    "revision_translation_affected": [
        {
            "value": true
        }
    ],
    "path": [
        {
            "alias": "\/canciones\/belitza-y-ambraham\/amarte-es-un-deleite",
            "langcode": "es",
            "pathauto": 1
        }
    ],
    "field_artista": [
        {
            "target_type": "taxonomy_term",
            "target_uuid": "3cd41af3-6b23-45bc-84f9-1dd5e793c079"
        }
    ],
    "field_bpm": [],
    "field_descripcion": [],
    "field_letra": [],
    "field_secuencia": [],
    "field_tags": [
        {
            "target_type": "taxonomy_term",
            "target_uuid": "56fc928e-a471-40bf-a79c-de6fdfb42ce8"
        }
    ],
    "field_tipo": [
        {
            "value": "Lenta"
        }
    ],
    "field_tipo_de_voz": [
        {
            "value": "Ambas"
        }
    ],
    "field_tono": [
        {
            "target_type": "taxonomy_term",
            "target_uuid": "b4e5e7ab-a2b9-4771-b6fa-a4446946b246"
        }
    ],
    "field_video": [
        {
            "value": "https:\/\/www.youtube.com\/watch?v=hAOqizObzZU"
        }
    ]
}